jk_logging/AbstractLogger.py
jk_logging/BufferLogger.py
jk_logging/ConsoleLogger.py
jk_logging/DetectionLogger.py
jk_logging/DetectionLogger_v0.py
jk_logging/EnumExtensitivity.py
jk_logging/EnumLogLevel.py
jk_logging/ExceptionInChildContextException.py
jk_logging/FileLogger.py
jk_logging/FilterLogger.py
jk_logging/ILogger.py
jk_logging/InvalidExtraArgumentsException.py
jk_logging/JSONFileLogger.py
jk_logging/LoggerInstanceManager.py
jk_logging/MulticastLogger.py
jk_logging/NamedMulticastLogger.py
jk_logging/NullLogger.py
jk_logging/SimpleFileLogger.py
jk_logging/StringListBuffer.py
jk_logging/StringListLogger.py
jk_logging/WithholdingLogger.py
jk_logging/____BufferLogger_old1.py.OLD
jk_logging/____BufferLogger_old2.py.OLD
jk_logging/____JSONListLogger.py
jk_logging/__init__.py
jk_logging/_inst.py
jk_logging/_nestEx.py
jk_logging/_wrapMain.py
jk_logging/annotation_logDescend.py
jk_logging/debugging/DebugTimeStampFormatter.py
jk_logging/debugging/__init__.py
jk_logging/fmt/AbstractLogMessageFormatter.py
jk_logging/fmt/AbstractTimeStampFormatter.py
jk_logging/fmt/ColoredLogMessageFormatter.py
jk_logging/fmt/DefaultTimeStampFormatter.py
jk_logging/fmt/HTMLLogMessageFormatter.py
jk_logging/fmt/JSONLogMessageFormatter.py
jk_logging/fmt/LogMessageFormatter.py
jk_logging/fmt/NoopTimeStampFormatter.py
jk_logging/fmt/__init__.py
jk_logging/impl/Converter.py
jk_logging/impl/Converter_compactJSON_to_raw.py
jk_logging/impl/Converter_prettyJSON_to_raw.py
jk_logging/impl/Converter_raw_to_compactJSON.py
jk_logging/impl/Converter_raw_to_prettyJSON.py
jk_logging/impl/IDCounter.py
jk_logging/impl/JSONDict.py
jk_logging/impl/LogStats.py
jk_logging/impl/ReadOnlyDict.py
jk_logging/impl/RollOverLogFile.py
jk_logging/impl/__init__.py
jk_logging/impl/createLogMsgTypeStrMap.py
jk_logging-0.2025.5.17.1.dist-info/WHEEL
jk_logging-0.2025.5.17.1.dist-info/METADATA
jk_logging-0.2025.5.17.1.dist-info/RECORD
