Metadata-Version: 2.1
Name: jk_logging
Version: 0.2025.5.17.1
Summary: This is a logging framework.
Keywords: exception handling,debugging,logging
Author-email: Jürgen Knauth <pubsrc@binary-overflow.de>
Maintainer-email: Jürgen Knauth <pubsrc@binary-overflow.de>
Requires-Python: >=3.8
Classifier: Development Status :: 5 - Production/Stable
Classifier: License :: OSI Approved :: Apache Software License
Classifier: Programming Language :: Python :: 3
Classifier: Topic :: Software Development :: Testing
Classifier: Topic :: System :: Logging
Requires-Dist: jk_exceptionhelper >= 0.2025.5.17
